powerext/__init__.py
powerext/common.py
powerext/git.py
powerext/git_power_ext.py
powerext/read_input_helper.py
git_power_ext-0.1.63.dist-info/LICENSE
git_power_ext-0.1.63.dist-info/METADATA
git_power_ext-0.1.63.dist-info/WHEEL
git_power_ext-0.1.63.dist-info/entry_points.txt
git_power_ext-0.1.63.dist-info/top_level.txt
git_power_ext-0.1.63.dist-info/RECORD
