Metadata-Version: 2.1
Name: git-power-ext
Version: 0.1.63
Summary: UNKNOWN
Home-page: UNKNOWN
Author: Mohamed Farouk
Author-email: mohamed.farouk173@gmail.com
License: UNKNOWN
Platform: UNKNOWN
Requires-Dist: Click
